djutils_core/__init__.py
djutils_core-0.1.0.dev0.dist-info/LICENSE
djutils_core-0.1.0.dev0.dist-info/METADATA
djutils_core-0.1.0.dev0.dist-info/WHEEL
djutils_core-0.1.0.dev0.dist-info/top_level.txt
djutils_core-0.1.0.dev0.dist-info/RECORD
