Metadata-Version: 2.1
Name: djutils-core
Version: 0.1.0.dev0
Summary: Django Project Utilities - Core
Author-email: ruriazz <azizruri.s@gmail.com>
Project-URL: Homepage, https://github.com/ruriazz/djutils-core
Project-URL: Bug Tracker, https://github.com/ruriazz/djutils-core/issues
Keywords: djutils_core
Classifier: Operating System :: OS Independent
Classifier: Programming Language :: Python
Classifier: Programming Language :: Python :: 3.11
Requires-Python: >=3.11
License-File: LICENSE
